{
  "status": [
    {
      "_id": "5edf8982ca0d9d132cd3b8dd",
      "name": "Nová"
    },
    {
      "_id": "5edf8982ca0d9d132cd3b8df",
      "name": "Registrované dopravcom"
    },
    {
      "_id": "5edf8982ca0d9d132cd3b8e0",
      "name": "V sklade, pripravené na vyzdvihnutie kuriérom"
    },
    {
      "_id": "5edf8982ca0d9d132cd3b8e2",
      "name": "Doručená"
    },
    {
      "_id": "5edf8982ca0d9d132cd3b8e1",
      "name": "Recenzované a schvalené"
    }
  ],
  "prices": [
    {
      "_id": "5ef89dcd56f69d17643556e8",
      "price": 1.50
    }
  ],
  "invoices": [
    {
      "_id": "5f6722d8595bb86b26db3ae0",
      "invoice": "eb5377322765cde00ebb8986e65430ea.pdf",
      "account": "d16e87c63d4433d07fcdfffdb0597d87"
    }
  ],
  "shipments": [
    {
      "courier": 4,
      "parcelId": 1,
      "from": "Slovakia, Nesvady",
      "to": "Slovakia, Nitra",
      "status": "5edf8982ca0d9d132cd3b8df",
      "price": 8.50,
      "express": false,
      "invoice": "5f6722d8595bb86b26db3ae0"
    }
  ]
}